luainstaller/__init__.py
luainstaller/cli.py
luainstaller/dependency_analyzer.py
luainstaller/engine.py
luainstaller/exceptions.py
luainstaller/gui.py
luainstaller/logger.py
luainstaller/source_bundler.py
luainstaller/srlua/__init__.py
luainstaller/srlua/linux/glue515
luainstaller/srlua/linux/glue515-32
luainstaller/srlua/linux/glue548
luainstaller/srlua/linux/srlua515
luainstaller/srlua/linux/srlua515-32
luainstaller/srlua/linux/srlua548
luainstaller/srlua/windows/glue515-32.exe
luainstaller/srlua/windows/glue515.exe
luainstaller/srlua/windows/glue548.exe
luainstaller/srlua/windows/srlua515-32.exe
luainstaller/srlua/windows/srlua515.exe
luainstaller/srlua/windows/srlua548.exe
luainstaller-2.0.0.data/data/share/man/man1/luainstaller.1
luainstaller-2.0.0.dist-info/licenses/LICENSE
luainstaller-2.0.0.dist-info/METADATA
luainstaller-2.0.0.dist-info/WHEEL
luainstaller-2.0.0.dist-info/entry_points.txt
luainstaller-2.0.0.dist-info/top_level.txt
luainstaller-2.0.0.dist-info/RECORD
