Metadata-Version: 2.4
Name: luainstaller
Version: 2.0.0
Summary: Package Lua scripts into standalone executables with multi-engine support
Author-email: WaterRun <linzhangrun49@gmail.com>
Maintainer-email: WaterRun <linzhangrun49@gmail.com>
License: LGPL-3.0-or-later
Project-URL: Homepage, https://github.com/Water-Run/luainstaller
Project-URL: Repository, https://github.com/Water-Run/luainstaller
Project-URL: Documentation, https://github.com/Water-Run/luainstaller/blob/main/README.md
Project-URL: Issues, https://github.com/Water-Run/luainstaller/issues
Keywords: lua,luastatic,srlua,compiler,executable,binary,packaging,dependency-analysis
Classifier: Development Status :: 4 - Beta
Classifier: Environment :: Console
Classifier: Environment :: X11 Applications :: GTK
Classifier: Environment :: Win32 (MS Windows)
Classifier: Intended Audience :: Developers
Classifier: License :: OSI Approved :: GNU Lesser General Public License v3 or later (LGPLv3+)
Classifier: Operating System :: POSIX :: Linux
Classifier: Operating System :: Microsoft :: Windows
Classifier: Programming Language :: Python :: 3
Classifier: Programming Language :: Python :: 3.10
Classifier: Programming Language :: Python :: 3.11
Classifier: Programming Language :: Python :: 3.12
Classifier: Programming Language :: Python :: 3.13
Classifier: Programming Language :: Python :: 3.14
Classifier: Topic :: Software Development :: Build Tools
Classifier: Topic :: Software Development :: Compilers
Classifier: Typing :: Typed
Requires-Python: >=3.10
License-File: LICENSE
Requires-Dist: simpsave>=10.1.0
Dynamic: license-file
